finutils/__init__.py
finutils/data.py
finutils-0.0.2.dist-info/LICENSE
finutils-0.0.2.dist-info/METADATA
finutils-0.0.2.dist-info/WHEEL
finutils-0.0.2.dist-info/top_level.txt
finutils-0.0.2.dist-info/RECORD
