Metadata-Version: 2.1
Name: finutils
Version: 0.0.2
Summary: Finutils is a collection of some finance related python utilities.
Home-page: https://github.com/blmhemu/finutils
Author: Hemanth Bollamreddi
Author-email: blmhemu@gmail.com
License: MIT
Keywords: finutils,cached pandas datareader
Platform: any
Classifier: Development Status :: 3 - Alpha
Classifier: Intended Audience :: Developers
Classifier: License :: OSI Approved :: MIT License
Classifier: Operating System :: OS Independent
Classifier: Programming Language :: Python :: 3 :: Only
Classifier: Programming Language :: Python :: 3
Classifier: Programming Language :: Python :: 3.7
Classifier: Topic :: Office/Business :: Financial
Classifier: Topic :: Office/Business :: Financial :: Investment
Classifier: Topic :: Software Development :: Libraries
Classifier: Topic :: Software Development :: Libraries :: Python Modules
Requires-Python: >=3.7
Requires-Dist: pandas (>=1.1.0)
Requires-Dist: pandas-datareader (>=0.9.0)
Requires-Dist: importlib-metadata (>=1.7.0)
Requires-Dist: readme-renderer (>=26.0)
